{
  "code": "A015260",
  "prices": [
    {
      "date": "2023-04-03",
      "price": 2230,
      "open": 2150,
      "high": 2290,
      "low": 2150,
      "volume": 740351
    },
    {
      "date": "2023-04-04",
      "price": 2250,
      "open": 2220,
      "high": 2305,
      "low": 2185,
      "volume": 449819
    },
    {
      "date": "2023-04-05",
      "price": 2310,
      "open": 2205,
      "high": 2330,
      "low": 2205,
      "volume": 448890
    },
    {
      "date": "2023-04-06",
      "price": 2300,
      "open": 2340,
      "high": 2400,
      "low": 2255,
      "volume": 469345
    },
    {
      "date": "2023-04-07",
      "price": 2345,
      "open": 2305,
      "high": 2530,
      "low": 2270,
      "volume": 2712066
    },
    {
      "date": "2023-04-10",
      "price": 2355,
      "open": 2395,
      "high": 2415,
      "low": 2180,
      "volume": 949986
    },
    {
      "date": "2023-04-11",
      "price": 2305,
      "open": 2350,
      "high": 2450,
      "low": 2270,
      "volume": 1000635
    },
    {
      "date": "2023-04-12",
      "price": 2290,
      "open": 2305,
      "high": 2330,
      "low": 2255,
      "volume": 406112
    },
    {
      "date": "2023-04-13",
      "price": 2330,
      "open": 2290,
      "high": 2415,
      "low": 2200,
      "volume": 936724
    },
    {
      "date": "2023-04-14",
      "price": 2425,
      "open": 2330,
      "high": 2430,
      "low": 2330,
      "volume": 846076
    },
    {
      "date": "2023-04-17",
      "price": 2420,
      "open": 2430,
      "high": 2490,
      "low": 2375,
      "volume": 458649
    },
    {
      "date": "2023-04-18",
      "price": 2485,
      "open": 2425,
      "high": 2600,
      "low": 2310,
      "volume": 2546292
    },
    {
      "date": "2023-04-19",
      "price": 2545,
      "open": 2495,
      "high": 2590,
      "low": 2485,
      "volume": 721396
    },
    {
      "date": "2023-04-20",
      "price": 2540,
      "open": 2510,
      "high": 2565,
      "low": 2490,
      "volume": 412741
    },
    {
      "date": "2023-04-21",
      "price": 2520,
      "open": 2530,
      "high": 2540,
      "low": 2420,
      "volume": 346391
    },
    {
      "date": "2023-04-24",
      "price": 2355,
      "open": 2545,
      "high": 2545,
      "low": 2320,
      "volume": 467635
    },
    {
      "date": "2023-04-25",
      "price": 2430,
      "open": 2395,
      "high": 2450,
      "low": 2300,
      "volume": 428583
    },
    {
      "date": "2023-04-26",
      "price": 2410,
      "open": 2460,
      "high": 2460,
      "low": 2360,
      "volume": 226403
    },
    {
      "date": "2023-04-27",
      "price": 2465,
      "open": 2530,
      "high": 2550,
      "low": 2410,
      "volume": 620954
    },
    {
      "date": "2023-04-28",
      "price": 2555,
      "open": 2470,
      "high": 2580,
      "low": 2420,
      "volume": 1263640
    },
    {
      "date": "2023-05-02",
      "price": 2540,
      "open": 2580,
      "high": 2620,
      "low": 2520,
      "volume": 643777
    },
    {
      "date": "2023-05-03",
      "price": 2470,
      "open": 2465,
      "high": 2510,
      "low": 2440,
      "volume": 406012
    },
    {
      "date": "2023-05-04",
      "price": 2375,
      "open": 2470,
      "high": 2470,
      "low": 2315,
      "volume": 534437
    },
    {
      "date": "2023-05-08",
      "price": 2340,
      "open": 2405,
      "high": 2470,
      "low": 2340,
      "volume": 278887
    },
    {
      "date": "2023-05-09",
      "price": 2210,
      "open": 2335,
      "high": 2400,
      "low": 2195,
      "volume": 545837
    },
    {
      "date": "2023-05-10",
      "price": 2380,
      "open": 2240,
      "high": 2430,
      "low": 2220,
      "volume": 560514
    },
    {
      "date": "2023-05-11",
      "price": 2450,
      "open": 2385,
      "high": 2500,
      "low": 2370,
      "volume": 545988
    },
    {
      "date": "2023-05-12",
      "price": 2320,
      "open": 2475,
      "high": 2520,
      "low": 2250,
      "volume": 2168560
    },
    {
      "date": "2023-05-15",
      "price": 2100,
      "open": 2340,
      "high": 2355,
      "low": 1934,
      "volume": 3474871
    },
    {
      "date": "2023-05-16",
      "price": 2040,
      "open": 2110,
      "high": 2140,
      "low": 2000,
      "volume": 483720
    },
    {
      "date": "2023-05-17",
      "price": 2070,
      "open": 2040,
      "high": 2075,
      "low": 1967,
      "volume": 344319
    },
    {
      "date": "2023-05-18",
      "price": 2015,
      "open": 2075,
      "high": 2075,
      "low": 1990,
      "volume": 407554
    },
    {
      "date": "2023-05-19",
      "price": 1939,
      "open": 2005,
      "high": 2010,
      "low": 1916,
      "volume": 532504
    },
    {
      "date": "2023-05-22",
      "price": 1999,
      "open": 1939,
      "high": 2040,
      "low": 1901,
      "volume": 237202
    },
    {
      "date": "2023-05-23",
      "price": 1996,
      "open": 1983,
      "high": 2065,
      "low": 1983,
      "volume": 192697
    },
    {
      "date": "2023-05-24",
      "price": 2000,
      "open": 1983,
      "high": 2040,
      "low": 1960,
      "volume": 173389
    },
    {
      "date": "2023-05-25",
      "price": 1989,
      "open": 2000,
      "high": 2010,
      "low": 1966,
      "volume": 158925
    },
    {
      "date": "2023-05-26",
      "price": 1934,
      "open": 1989,
      "high": 1989,
      "low": 1896,
      "volume": 374107
    },
    {
      "date": "2023-05-30",
      "price": 1924,
      "open": 1934,
      "high": 1972,
      "low": 1902,
      "volume": 96549
    },
    {
      "date": "2023-05-31",
      "price": 1895,
      "open": 1932,
      "high": 1932,
      "low": 1800,
      "volume": 180773
    },
    {
      "date": "2023-06-01",
      "price": 1896,
      "open": 1896,
      "high": 1952,
      "low": 1889,
      "volume": 170663
    },
    {
      "date": "2023-06-02",
      "price": 1861,
      "open": 1934,
      "high": 1934,
      "low": 1860,
      "volume": 258889
    },
    {
      "date": "2023-06-05",
      "price": 1890,
      "open": 1880,
      "high": 1906,
      "low": 1861,
      "volume": 128760
    },
    {
      "date": "2023-06-07",
      "price": 1850,
      "open": 1867,
      "high": 1904,
      "low": 1820,
      "volume": 147671
    },
    {
      "date": "2023-06-08",
      "price": 1799,
      "open": 1832,
      "high": 1860,
      "low": 1799,
      "volume": 139686
    },
    {
      "date": "2023-06-09",
      "price": 1792,
      "open": 1825,
      "high": 1829,
      "low": 1756,
      "volume": 173409
    },
    {
      "date": "2023-06-12",
      "price": 1766,
      "open": 1786,
      "high": 1824,
      "low": 1756,
      "volume": 174302
    },
    {
      "date": "2023-06-13",
      "price": 1798,
      "open": 1786,
      "high": 1891,
      "low": 1763,
      "volume": 395925
    },
    {
      "date": "2023-06-14",
      "price": 1769,
      "open": 1786,
      "high": 1819,
      "low": 1748,
      "volume": 236032
    },
    {
      "date": "2023-06-15",
      "price": 1734,
      "open": 1769,
      "high": 1777,
      "low": 1720,
      "volume": 160640
    },
    {
      "date": "2023-06-16",
      "price": 1751,
      "open": 1742,
      "high": 1780,
      "low": 1730,
      "volume": 137435
    },
    {
      "date": "2023-06-19",
      "price": 1892,
      "open": 1780,
      "high": 1907,
      "low": 1752,
      "volume": 532363
    },
    {
      "date": "2023-06-20",
      "price": 1821,
      "open": 1889,
      "high": 1916,
      "low": 1815,
      "volume": 174631
    },
    {
      "date": "2023-06-21",
      "price": 1795,
      "open": 1816,
      "high": 1842,
      "low": 1784,
      "volume": 112566
    },
    {
      "date": "2023-06-22",
      "price": 1765,
      "open": 1795,
      "high": 1802,
      "low": 1757,
      "volume": 119894
    },
    {
      "date": "2023-06-23",
      "price": 1770,
      "open": 1774,
      "high": 1800,
      "low": 1753,
      "volume": 72191
    },
    {
      "date": "2023-06-26",
      "price": 1772,
      "open": 1763,
      "high": 1787,
      "low": 1756,
      "volume": 70212
    },
    {
      "date": "2023-06-27",
      "price": 1769,
      "open": 1805,
      "high": 1806,
      "low": 1759,
      "volume": 99598
    },
    {
      "date": "2023-06-28",
      "price": 1766,
      "open": 1773,
      "high": 1803,
      "low": 1758,
      "volume": 92054
    },
    {
      "date": "2023-06-29",
      "price": 1740,
      "open": 1790,
      "high": 1790,
      "low": 1725,
      "volume": 122275
    },
    {
      "date": "2023-06-30",
      "price": 1736,
      "open": 1730,
      "high": 1768,
      "low": 1730,
      "volume": 55955
    },
    {
      "date": "2023-07-03",
      "price": 1729,
      "open": 1754,
      "high": 1794,
      "low": 1724,
      "volume": 123373
    },
    {
      "date": "2023-07-04",
      "price": 1738,
      "open": 1747,
      "high": 1780,
      "low": 1729,
      "volume": 124954
    },
    {
      "date": "2023-07-05",
      "price": 1688,
      "open": 1756,
      "high": 1769,
      "low": 1682,
      "volume": 136382
    },
    {
      "date": "2023-07-06",
      "price": 1634,
      "open": 1697,
      "high": 1697,
      "low": 1631,
      "volume": 127208
    },
    {
      "date": "2023-07-07",
      "price": 1661,
      "open": 1634,
      "high": 1675,
      "low": 1610,
      "volume": 70294
    },
    {
      "date": "2023-07-10",
      "price": 1719,
      "open": 1674,
      "high": 1727,
      "low": 1638,
      "volume": 110234
    },
    {
      "date": "2023-07-11",
      "price": 1700,
      "open": 1719,
      "high": 1725,
      "low": 1667,
      "volume": 84979
    },
    {
      "date": "2023-07-12",
      "price": 1625,
      "open": 1688,
      "high": 1700,
      "low": 1625,
      "volume": 90887
    },
    {
      "date": "2023-07-13",
      "price": 1623,
      "open": 1625,
      "high": 1667,
      "low": 1623,
      "volume": 64969
    },
    {
      "date": "2023-07-14",
      "price": 1630,
      "open": 1634,
      "high": 1672,
      "low": 1600,
      "volume": 164311
    },
    {
      "date": "2023-07-17",
      "price": 1643,
      "open": 1717,
      "high": 1717,
      "low": 1610,
      "volume": 115283
    },
    {
      "date": "2023-07-18",
      "price": 1628,
      "open": 1640,
      "high": 1708,
      "low": 1603,
      "volume": 97569
    },
    {
      "date": "2023-07-19",
      "price": 1593,
      "open": 1628,
      "high": 1628,
      "low": 1560,
      "volume": 186622
    },
    {
      "date": "2023-07-20",
      "price": 1619,
      "open": 1600,
      "high": 1635,
      "low": 1577,
      "volume": 150489
    },
    {
      "date": "2023-07-21",
      "price": 1591,
      "open": 1610,
      "high": 1619,
      "low": 1587,
      "volume": 88850
    },
    {
      "date": "2023-07-24",
      "price": 1560,
      "open": 1589,
      "high": 1589,
      "low": 1530,
      "volume": 134276
    },
    {
      "date": "2023-07-25",
      "price": 1525,
      "open": 1536,
      "high": 1559,
      "low": 1500,
      "volume": 169623
    },
    {
      "date": "2023-07-26",
      "price": 1509,
      "open": 1525,
      "high": 1525,
      "low": 1470,
      "volume": 245914
    },
    {
      "date": "2023-07-27",
      "price": 1560,
      "open": 1497,
      "high": 1574,
      "low": 1471,
      "volume": 56788
    },
    {
      "date": "2023-07-28",
      "price": 1603,
      "open": 1536,
      "high": 1623,
      "low": 1471,
      "volume": 96170
    },
    {
      "date": "2023-07-31",
      "price": 1597,
      "open": 1650,
      "high": 1680,
      "low": 1597,
      "volume": 89013
    },
    {
      "date": "2023-08-01",
      "price": 1620,
      "open": 1600,
      "high": 1680,
      "low": 1597,
      "volume": 85477
    },
    {
      "date": "2023-08-02",
      "price": 1556,
      "open": 1637,
      "high": 1637,
      "low": 1556,
      "volume": 98625
    },
    {
      "date": "2023-08-03",
      "price": 1566,
      "open": 1549,
      "high": 1572,
      "low": 1522,
      "volume": 39669
    },
    {
      "date": "2023-08-04",
      "price": 1596,
      "open": 1543,
      "high": 1599,
      "low": 1538,
      "volume": 30373
    },
    {
      "date": "2023-08-07",
      "price": 1590,
      "open": 1596,
      "high": 1611,
      "low": 1534,
      "volume": 37884
    },
    {
      "date": "2023-08-08",
      "price": 1537,
      "open": 1570,
      "high": 1588,
      "low": 1514,
      "volume": 111955
    },
    {
      "date": "2023-08-09",
      "price": 1532,
      "open": 1537,
      "high": 1545,
      "low": 1505,
      "volume": 72474
    },
    {
      "date": "2023-08-10",
      "price": 1540,
      "open": 1548,
      "high": 1593,
      "low": 1513,
      "volume": 156217
    },
    {
      "date": "2023-08-11",
      "price": 1683,
      "open": 1541,
      "high": 1725,
      "low": 1541,
      "volume": 573651
    },
    {
      "date": "2023-08-14",
      "price": 1629,
      "open": 1751,
      "high": 1751,
      "low": 1612,
      "volume": 180506
    },
    {
      "date": "2023-08-16",
      "price": 1624,
      "open": 1629,
      "high": 1631,
      "low": 1593,
      "volume": 102265
    },
    {
      "date": "2023-08-17",
      "price": 1731,
      "open": 1620,
      "high": 1790,
      "low": 1590,
      "volume": 690759
    },
    {
      "date": "2023-08-18",
      "price": 1797,
      "open": 1733,
      "high": 1825,
      "low": 1676,
      "volume": 337704
    },
    {
      "date": "2023-08-21",
      "price": 1753,
      "open": 1821,
      "high": 1868,
      "low": 1742,
      "volume": 428529
    },
    {
      "date": "2023-08-22",
      "price": 1728,
      "open": 1765,
      "high": 1860,
      "low": 1713,
      "volume": 369763
    },
    {
      "date": "2023-08-23",
      "price": 1680,
      "open": 1728,
      "high": 1728,
      "low": 1675,
      "volume": 133704
    },
    {
      "date": "2023-08-24",
      "price": 1695,
      "open": 1680,
      "high": 1717,
      "low": 1675,
      "volume": 31404
    },
    {
      "date": "2023-08-25",
      "price": 1693,
      "open": 1695,
      "high": 1721,
      "low": 1679,
      "volume": 37491
    },
    {
      "date": "2023-08-28",
      "price": 1660,
      "open": 1693,
      "high": 1737,
      "low": 1658,
      "volume": 102602
    },
    {
      "date": "2023-08-29",
      "price": 1654,
      "open": 1660,
      "high": 1679,
      "low": 1639,
      "volume": 109306
    },
    {
      "date": "2023-08-30",
      "price": 1661,
      "open": 1654,
      "high": 1678,
      "low": 1630,
      "volume": 145917
    },
    {
      "date": "2023-08-31",
      "price": 1680,
      "open": 1661,
      "high": 1698,
      "low": 1648,
      "volume": 79257
    },
    {
      "date": "2023-09-01",
      "price": 1653,
      "open": 1658,
      "high": 1701,
      "low": 1613,
      "volume": 125029
    },
    {
      "date": "2023-09-04",
      "price": 1659,
      "open": 1695,
      "high": 1695,
      "low": 1601,
      "volume": 149546
    },
    {
      "date": "2023-09-05",
      "price": 1679,
      "open": 1659,
      "high": 1694,
      "low": 1638,
      "volume": 51106
    },
    {
      "date": "2023-09-06",
      "price": 1660,
      "open": 1682,
      "high": 1708,
      "low": 1631,
      "volume": 39816
    },
    {
      "date": "2023-09-07",
      "price": 1652,
      "open": 1670,
      "high": 1670,
      "low": 1639,
      "volume": 35697
    },
    {
      "date": "2023-09-08",
      "price": 1650,
      "open": 1662,
      "high": 1662,
      "low": 1620,
      "volume": 58026
    },
    {
      "date": "2023-09-11",
      "price": 1615,
      "open": 1650,
      "high": 1660,
      "low": 1588,
      "volume": 127657
    },
    {
      "date": "2023-09-12",
      "price": 1658,
      "open": 1615,
      "high": 1776,
      "low": 1580,
      "volume": 706392
    },
    {
      "date": "2023-09-13",
      "price": 1621,
      "open": 1658,
      "high": 1660,
      "low": 1616,
      "volume": 68108
    },
    {
      "date": "2023-09-14",
      "price": 1654,
      "open": 1621,
      "high": 1668,
      "low": 1616,
      "volume": 90760
    },
    {
      "date": "2023-09-15",
      "price": 1654,
      "open": 1630,
      "high": 1654,
      "low": 1620,
      "volume": 88140
    },
    {
      "date": "2023-09-18",
      "price": 1627,
      "open": 1646,
      "high": 1646,
      "low": 1613,
      "volume": 68302
    },
    {
      "date": "2023-09-19",
      "price": 1597,
      "open": 1628,
      "high": 1628,
      "low": 1584,
      "volume": 124162
    },
    {
      "date": "2023-09-20",
      "price": 1581,
      "open": 1595,
      "high": 1629,
      "low": 1552,
      "volume": 97622
    },
    {
      "date": "2023-09-21",
      "price": 1542,
      "open": 1552,
      "high": 1597,
      "low": 1525,
      "volume": 72899
    },
    {
      "date": "2023-09-22",
      "price": 1550,
      "open": 1525,
      "high": 1573,
      "low": 1510,
      "volume": 136086
    },
    {
      "date": "2023-09-25",
      "price": 1530,
      "open": 1615,
      "high": 1615,
      "low": 1513,
      "volume": 24004
    },
    {
      "date": "2023-09-26",
      "price": 1505,
      "open": 1589,
      "high": 1589,
      "low": 1490,
      "volume": 59380
    },
    {
      "date": "2023-09-27",
      "price": 1506,
      "open": 1505,
      "high": 1540,
      "low": 1490,
      "volume": 26285
    },
    {
      "date": "2023-10-04",
      "price": 1493,
      "open": 1483,
      "high": 1630,
      "low": 1453,
      "volume": 190949
    },
    {
      "date": "2023-10-05",
      "price": 1491,
      "open": 1483,
      "high": 1514,
      "low": 1463,
      "volume": 65336
    },
    {
      "date": "2023-10-06",
      "price": 1490,
      "open": 1491,
      "high": 1526,
      "low": 1479,
      "volume": 36621
    },
    {
      "date": "2023-10-10",
      "price": 1475,
      "open": 1505,
      "high": 1505,
      "low": 1458,
      "volume": 77728
    },
    {
      "date": "2023-10-11",
      "price": 1483,
      "open": 1455,
      "high": 1495,
      "low": 1455,
      "volume": 8322
    },
    {
      "date": "2023-10-12",
      "price": 1479,
      "open": 1473,
      "high": 1499,
      "low": 1472,
      "volume": 20850
    },
    {
      "date": "2023-10-13",
      "price": 1470,
      "open": 1478,
      "high": 1496,
      "low": 1463,
      "volume": 29206
    },
    {
      "date": "2023-10-16",
      "price": 1450,
      "open": 1476,
      "high": 1476,
      "low": 1432,
      "volume": 68886
    },
    {
      "date": "2023-10-17",
      "price": 1444,
      "open": 1431,
      "high": 1471,
      "low": 1430,
      "volume": 24469
    },
    {
      "date": "2023-10-18",
      "price": 1415,
      "open": 1444,
      "high": 1444,
      "low": 1375,
      "volume": 191945
    },
    {
      "date": "2023-10-19",
      "price": 1415,
      "open": 1381,
      "high": 1420,
      "low": 1381,
      "volume": 46687
    },
    {
      "date": "2023-10-20",
      "price": 1370,
      "open": 1447,
      "high": 1447,
      "low": 1345,
      "volume": 117323
    },
    {
      "date": "2023-10-23",
      "price": 1380,
      "open": 1368,
      "high": 1385,
      "low": 1295,
      "volume": 109925
    },
    {
      "date": "2023-10-24",
      "price": 1321,
      "open": 1393,
      "high": 1393,
      "low": 1281,
      "volume": 106405
    },
    {
      "date": "2023-10-25",
      "price": 1281,
      "open": 1328,
      "high": 1350,
      "low": 1272,
      "volume": 61348
    },
    {
      "date": "2023-10-26",
      "price": 1249,
      "open": 1277,
      "high": 1279,
      "low": 1215,
      "volume": 120381
    },
    {
      "date": "2023-10-27",
      "price": 1226,
      "open": 1249,
      "high": 1259,
      "low": 1208,
      "volume": 54262
    },
    {
      "date": "2023-10-30",
      "price": 1230,
      "open": 1226,
      "high": 1240,
      "low": 1185,
      "volume": 92522
    },
    {
      "date": "2023-10-31",
      "price": 1230,
      "open": 1224,
      "high": 1261,
      "low": 1221,
      "volume": 21049
    },
    {
      "date": "2023-11-01",
      "price": 1230,
      "open": 1230,
      "high": 1234,
      "low": 1210,
      "volume": 32512
    },
    {
      "date": "2023-11-02",
      "price": 1238,
      "open": 1232,
      "high": 1281,
      "low": 1230,
      "volume": 53083
    },
    {
      "date": "2023-11-03",
      "price": 1252,
      "open": 1245,
      "high": 1270,
      "low": 1233,
      "volume": 87983
    },
    {
      "date": "2023-11-06",
      "price": 1287,
      "open": 1254,
      "high": 1293,
      "low": 1234,
      "volume": 114745
    },
    {
      "date": "2023-11-07",
      "price": 1300,
      "open": 1287,
      "high": 1330,
      "low": 1261,
      "volume": 67838
    },
    {
      "date": "2023-11-08",
      "price": 1301,
      "open": 1300,
      "high": 1318,
      "low": 1284,
      "volume": 45692
    },
    {
      "date": "2023-11-09",
      "price": 1250,
      "open": 1308,
      "high": 1308,
      "low": 1201,
      "volume": 51290
    },
    {
      "date": "2023-11-10",
      "price": 1222,
      "open": 1246,
      "high": 1247,
      "low": 1200,
      "volume": 113782
    },
    {
      "date": "2023-11-13",
      "price": 1520,
      "open": 1223,
      "high": 1587,
      "low": 1223,
      "volume": 3555404
    },
    {
      "date": "2023-11-14",
      "price": 1589,
      "open": 1566,
      "high": 1722,
      "low": 1532,
      "volume": 1440020
    },
    {
      "date": "2023-11-15",
      "price": 1628,
      "open": 1622,
      "high": 1643,
      "low": 1542,
      "volume": 548922
    },
    {
      "date": "2023-11-16",
      "price": 1658,
      "open": 1628,
      "high": 1669,
      "low": 1602,
      "volume": 200051
    },
    {
      "date": "2023-11-17",
      "price": 1640,
      "open": 1679,
      "high": 1680,
      "low": 1594,
      "volume": 199981
    },
    {
      "date": "2023-11-20",
      "price": 1800,
      "open": 1638,
      "high": 1851,
      "low": 1590,
      "volume": 1098083
    },
    {
      "date": "2023-11-21",
      "price": 1792,
      "open": 1783,
      "high": 1891,
      "low": 1740,
      "volume": 569566
    },
    {
      "date": "2023-11-22",
      "price": 1674,
      "open": 1792,
      "high": 1826,
      "low": 1650,
      "volume": 749043
    },
    {
      "date": "2023-11-23",
      "price": 1688,
      "open": 1670,
      "high": 1743,
      "low": 1628,
      "volume": 334262
    },
    {
      "date": "2023-11-24",
      "price": 1627,
      "open": 1686,
      "high": 1686,
      "low": 1625,
      "volume": 271875
    },
    {
      "date": "2023-11-27",
      "price": 1549,
      "open": 1627,
      "high": 1627,
      "low": 1515,
      "volume": 352509
    },
    {
      "date": "2023-11-28",
      "price": 1476,
      "open": 1549,
      "high": 1549,
      "low": 1433,
      "volume": 346545
    },
    {
      "date": "2023-11-29",
      "price": 1436,
      "open": 1476,
      "high": 1476,
      "low": 1418,
      "volume": 138994
    },
    {
      "date": "2023-11-30",
      "price": 1410,
      "open": 1436,
      "high": 1436,
      "low": 1350,
      "volume": 274776
    },
    {
      "date": "2023-12-01",
      "price": 1346,
      "open": 1398,
      "high": 1409,
      "low": 1337,
      "volume": 209980
    },
    {
      "date": "2023-12-04",
      "price": 1404,
      "open": 1345,
      "high": 1430,
      "low": 1310,
      "volume": 153036
    },
    {
      "date": "2023-12-05",
      "price": 1578,
      "open": 1401,
      "high": 1578,
      "low": 1401,
      "volume": 352902
    },
    {
      "date": "2023-12-06",
      "price": 1450,
      "open": 1599,
      "high": 1619,
      "low": 1437,
      "volume": 321154
    },
    {
      "date": "2023-12-07",
      "price": 1482,
      "open": 1451,
      "high": 1533,
      "low": 1451,
      "volume": 135250
    },
    {
      "date": "2023-12-08",
      "price": 1482,
      "open": 1472,
      "high": 1527,
      "low": 1452,
      "volume": 69527
    },
    {
      "date": "2023-12-11",
      "price": 1468,
      "open": 1458,
      "high": 1519,
      "low": 1451,
      "volume": 79372
    },
    {
      "date": "2023-12-12",
      "price": 1421,
      "open": 1455,
      "high": 1509,
      "low": 1421,
      "volume": 102730
    },
    {
      "date": "2023-12-13",
      "price": 1416,
      "open": 1468,
      "high": 1468,
      "low": 1400,
      "volume": 53333
    },
    {
      "date": "2023-12-14",
      "price": 1419,
      "open": 1420,
      "high": 1438,
      "low": 1400,
      "volume": 100836
    },
    {
      "date": "2023-12-15",
      "price": 1410,
      "open": 1411,
      "high": 1445,
      "low": 1387,
      "volume": 116144
    },
    {
      "date": "2023-12-18",
      "price": 1430,
      "open": 1400,
      "high": 1468,
      "low": 1392,
      "volume": 100585
    },
    {
      "date": "2023-12-19",
      "price": 1431,
      "open": 1411,
      "high": 1445,
      "low": 1401,
      "volume": 42828
    },
    {
      "date": "2023-12-20",
      "price": 1432,
      "open": 1415,
      "high": 1467,
      "low": 1415,
      "volume": 67495
    },
    {
      "date": "2023-12-21",
      "price": 1445,
      "open": 1421,
      "high": 1460,
      "low": 1421,
      "volume": 82812
    },
    {
      "date": "2023-12-22",
      "price": 1457,
      "open": 1445,
      "high": 1515,
      "low": 1432,
      "volume": 204875
    },
    {
      "date": "2023-12-26",
      "price": 1405,
      "open": 1479,
      "high": 1479,
      "low": 1405,
      "volume": 86520
    },
    {
      "date": "2023-12-27",
      "price": 1331,
      "open": 1410,
      "high": 1428,
      "low": 1331,
      "volume": 134850
    },
    {
      "date": "2023-12-28",
      "price": 1350,
      "open": 1345,
      "high": 1398,
      "low": 1325,
      "volume": 290230
    },
    {
      "date": "2024-01-02",
      "price": 1463,
      "open": 1350,
      "high": 1497,
      "low": 1350,
      "volume": 156043
    },
    {
      "date": "2024-01-03",
      "price": 1519,
      "open": 1465,
      "high": 1540,
      "low": 1433,
      "volume": 146564
    },
    {
      "date": "2024-01-04",
      "price": 1535,
      "open": 1500,
      "high": 1590,
      "low": 1490,
      "volume": 235150
    },
    {
      "date": "2024-01-05",
      "price": 1483,
      "open": 1535,
      "high": 1650,
      "low": 1466,
      "volume": 328364
    },
    {
      "date": "2024-01-08",
      "price": 1475,
      "open": 1543,
      "high": 1543,
      "low": 1400,
      "volume": 173497
    },
    {
      "date": "2024-01-09",
      "price": 1478,
      "open": 1470,
      "high": 1500,
      "low": 1465,
      "volume": 87451
    },
    {
      "date": "2024-01-10",
      "price": 1411,
      "open": 1478,
      "high": 1508,
      "low": 1411,
      "volume": 166535
    },
    {
      "date": "2024-01-11",
      "price": 1420,
      "open": 1400,
      "high": 1446,
      "low": 1375,
      "volume": 185795
    },
    {
      "date": "2024-01-12",
      "price": 1351,
      "open": 1387,
      "high": 1418,
      "low": 1351,
      "volume": 139557
    },
    {
      "date": "2024-01-15",
      "price": 1302,
      "open": 1351,
      "high": 1361,
      "low": 1297,
      "volume": 195453
    },
    {
      "date": "2024-01-16",
      "price": 1295,
      "open": 1310,
      "high": 1310,
      "low": 1270,
      "volume": 133413
    },
    {
      "date": "2024-01-17",
      "price": 1274,
      "open": 1287,
      "high": 1289,
      "low": 1251,
      "volume": 54956
    },
    {
      "date": "2024-01-18",
      "price": 1304,
      "open": 1282,
      "high": 1316,
      "low": 1274,
      "volume": 94783
    },
    {
      "date": "2024-01-19",
      "price": 1271,
      "open": 1319,
      "high": 1333,
      "low": 1261,
      "volume": 127497
    },
    {
      "date": "2024-01-22",
      "price": 1231,
      "open": 1271,
      "high": 1271,
      "low": 1230,
      "volume": 133321
    },
    {
      "date": "2024-01-23",
      "price": 1263,
      "open": 1222,
      "high": 1264,
      "low": 1190,
      "volume": 98303
    },
    {
      "date": "2024-01-24",
      "price": 1217,
      "open": 1240,
      "high": 1262,
      "low": 1204,
      "volume": 133478
    },
    {
      "date": "2024-01-25",
      "price": 1200,
      "open": 1218,
      "high": 1218,
      "low": 1160,
      "volume": 182415
    },
    {
      "date": "2024-01-26",
      "price": 1199,
      "open": 1242,
      "high": 1242,
      "low": 1183,
      "volume": 88170
    },
    {
      "date": "2024-01-29",
      "price": 1199,
      "open": 1199,
      "high": 1217,
      "low": 1165,
      "volume": 105895
    },
    {
      "date": "2024-01-30",
      "price": 1188,
      "open": 1193,
      "high": 1199,
      "low": 1168,
      "volume": 39909
    },
    {
      "date": "2024-01-31",
      "price": 1123,
      "open": 1155,
      "high": 1199,
      "low": 1120,
      "volume": 306955
    },
    {
      "date": "2024-02-01",
      "price": 1112,
      "open": 1126,
      "high": 1129,
      "low": 1091,
      "volume": 132995
    },
    {
      "date": "2024-02-02",
      "price": 1140,
      "open": 1095,
      "high": 1172,
      "low": 1095,
      "volume": 89422
    },
    {
      "date": "2024-02-05",
      "price": 1093,
      "open": 1118,
      "high": 1152,
      "low": 1092,
      "volume": 146145
    },
    {
      "date": "2024-02-06",
      "price": 1065,
      "open": 1090,
      "high": 1092,
      "low": 1053,
      "volume": 123641
    },
    {
      "date": "2024-02-07",
      "price": 1048,
      "open": 1066,
      "high": 1085,
      "low": 1048,
      "volume": 94264
    },
    {
      "date": "2024-02-08",
      "price": 1074,
      "open": 1078,
      "high": 1090,
      "low": 1034,
      "volume": 122748
    },
    {
      "date": "2024-02-13",
      "price": 1091,
      "open": 1070,
      "high": 1140,
      "low": 1070,
      "volume": 72650
    },
    {
      "date": "2024-02-14",
      "price": 1052,
      "open": 1090,
      "high": 1090,
      "low": 1040,
      "volume": 173924
    },
    {
      "date": "2024-02-15",
      "price": 1119,
      "open": 1053,
      "high": 1120,
      "low": 1053,
      "volume": 177465
    },
    {
      "date": "2024-02-16",
      "price": 1100,
      "open": 1159,
      "high": 1159,
      "low": 1087,
      "volume": 147840
    },
    {
      "date": "2024-02-19",
      "price": 1085,
      "open": 1100,
      "high": 1100,
      "low": 1076,
      "volume": 104344
    },
    {
      "date": "2024-02-20",
      "price": 1076,
      "open": 1085,
      "high": 1085,
      "low": 1041,
      "volume": 146688
    },
    {
      "date": "2024-02-21",
      "price": 1070,
      "open": 1076,
      "high": 1076,
      "low": 1059,
      "volume": 42369
    },
    {
      "date": "2024-02-22",
      "price": 1070,
      "open": 1070,
      "high": 1086,
      "low": 1058,
      "volume": 89050
    },
    {
      "date": "2024-02-23",
      "price": 1030,
      "open": 1061,
      "high": 1090,
      "low": 1030,
      "volume": 157692
    },
    {
      "date": "2024-02-26",
      "price": 1012,
      "open": 1045,
      "high": 1045,
      "low": 1004,
      "volume": 178483
    },
    {
      "date": "2024-02-27",
      "price": 1011,
      "open": 1020,
      "high": 1028,
      "low": 1009,
      "volume": 59410
    },
    {
      "date": "2024-02-28",
      "price": 1042,
      "open": 1011,
      "high": 1042,
      "low": 999,
      "volume": 116577
    },
    {
      "date": "2024-02-29",
      "price": 1193,
      "open": 1050,
      "high": 1354,
      "low": 1042,
      "volume": 10038264
    },
    {
      "date": "2024-03-04",
      "price": 1165,
      "open": 1162,
      "high": 1233,
      "low": 1116,
      "volume": 746214
    },
    {
      "date": "2024-03-05",
      "price": 1123,
      "open": 1153,
      "high": 1210,
      "low": 1118,
      "volume": 383379
    },
    {
      "date": "2024-03-06",
      "price": 1147,
      "open": 1145,
      "high": 1194,
      "low": 1100,
      "volume": 252063
    },
    {
      "date": "2024-03-07",
      "price": 1120,
      "open": 1147,
      "high": 1155,
      "low": 1107,
      "volume": 182456
    },
    {
      "date": "2024-03-08",
      "price": 1071,
      "open": 1125,
      "high": 1125,
      "low": 1061,
      "volume": 268914
    },
    {
      "date": "2024-03-11",
      "price": 1069,
      "open": 1071,
      "high": 1076,
      "low": 1057,
      "volume": 61252
    },
    {
      "date": "2024-03-12",
      "price": 1082,
      "open": 1060,
      "high": 1090,
      "low": 1059,
      "volume": 85229
    },
    {
      "date": "2024-03-13",
      "price": 1078,
      "open": 1082,
      "high": 1097,
      "low": 1070,
      "volume": 55988
    },
    {
      "date": "2024-03-14",
      "price": 1078,
      "open": 1078,
      "high": 1090,
      "low": 1066,
      "volume": 47169
    },
    {
      "date": "2024-03-15",
      "price": 1040,
      "open": 1068,
      "high": 1096,
      "low": 1040,
      "volume": 104449
    },
    {
      "date": "2024-03-18",
      "price": 1060,
      "open": 1044,
      "high": 1067,
      "low": 1040,
      "volume": 62451
    },
    {
      "date": "2024-03-19",
      "price": 1041,
      "open": 1060,
      "high": 1060,
      "low": 1031,
      "volume": 65849
    },
    {
      "date": "2024-03-20",
      "price": 1043,
      "open": 1040,
      "high": 1059,
      "low": 1040,
      "volume": 38349
    },
    {
      "date": "2024-03-21",
      "price": 1075,
      "open": 1053,
      "high": 1076,
      "low": 1050,
      "volume": 92915
    },
    {
      "date": "2024-03-22",
      "price": 1250,
      "open": 1062,
      "high": 1319,
      "low": 1062,
      "volume": 3261669
    },
    {
      "date": "2024-03-25",
      "price": 1240,
      "open": 1250,
      "high": 1282,
      "low": 1201,
      "volume": 415792
    },
    {
      "date": "2024-03-26",
      "price": 1181,
      "open": 1252,
      "high": 1252,
      "low": 1171,
      "volume": 189194
    },
    {
      "date": "2024-03-27",
      "price": 1174,
      "open": 1181,
      "high": 1190,
      "low": 1137,
      "volume": 87259
    },
    {
      "date": "2024-03-28",
      "price": 1201,
      "open": 1155,
      "high": 1363,
      "low": 1141,
      "volume": 1387783
    },
    {
      "date": "2024-03-29",
      "price": 1220,
      "open": 1201,
      "high": 1248,
      "low": 1180,
      "volume": 130192
    },
    {
      "date": "2024-04-01",
      "price": 1240,
      "open": 1225,
      "high": 1268,
      "low": 1211,
      "volume": 151611
    },
    {
      "date": "2024-04-02",
      "price": 1198,
      "open": 1245,
      "high": 1277,
      "low": 1195,
      "volume": 77034
    },
    {
      "date": "2024-04-03",
      "price": 1200,
      "open": 1180,
      "high": 1221,
      "low": 1177,
      "volume": 50824
    },
    {
      "date": "2024-04-04",
      "price": 1200,
      "open": 1199,
      "high": 1212,
      "low": 1152,
      "volume": 54200
    },
    {
      "date": "2024-04-05",
      "price": 1186,
      "open": 1199,
      "high": 1200,
      "low": 1160,
      "volume": 48019
    },
    {
      "date": "2024-04-08",
      "price": 1180,
      "open": 1182,
      "high": 1219,
      "low": 1162,
      "volume": 86487
    },
    {
      "date": "2024-04-09",
      "price": 1205,
      "open": 1180,
      "high": 1208,
      "low": 1172,
      "volume": 35848
    },
    {
      "date": "2024-04-11",
      "price": 1170,
      "open": 1204,
      "high": 1204,
      "low": 1161,
      "volume": 37911
    },
    {
      "date": "2024-04-12",
      "price": 1153,
      "open": 1164,
      "high": 1180,
      "low": 1125,
      "volume": 110891
    },
    {
      "date": "2024-04-15",
      "price": 1119,
      "open": 1145,
      "high": 1145,
      "low": 1080,
      "volume": 108345
    },
    {
      "date": "2024-04-16",
      "price": 1090,
      "open": 1114,
      "high": 1114,
      "low": 1078,
      "volume": 57652
    },
    {
      "date": "2024-04-17",
      "price": 1095,
      "open": 1090,
      "high": 1099,
      "low": 1073,
      "volume": 63648
    },
    {
      "date": "2024-04-18",
      "price": 1098,
      "open": 1089,
      "high": 1120,
      "low": 1060,
      "volume": 88263
    },
    {
      "date": "2024-04-19",
      "price": 1120,
      "open": 1101,
      "high": 1296,
      "low": 1098,
      "volume": 1818081
    },
    {
      "date": "2024-04-22",
      "price": 1153,
      "open": 1122,
      "high": 1280,
      "low": 1122,
      "volume": 739844
    },
    {
      "date": "2024-04-23",
      "price": 1175,
      "open": 1153,
      "high": 1200,
      "low": 1143,
      "volume": 95896
    },
    {
      "date": "2024-04-24",
      "price": 1167,
      "open": 1170,
      "high": 1187,
      "low": 1115,
      "volume": 82437
    },
    {
      "date": "2024-04-25",
      "price": 1173,
      "open": 1167,
      "high": 1187,
      "low": 1147,
      "volume": 90574
    },
    {
      "date": "2024-04-26",
      "price": 1168,
      "open": 1166,
      "high": 1173,
      "low": 1160,
      "volume": 74717
    },
    {
      "date": "2024-04-29",
      "price": 1160,
      "open": 1168,
      "high": 1178,
      "low": 1151,
      "volume": 82409
    },
    {
      "date": "2024-04-30",
      "price": 1150,
      "open": 1160,
      "high": 1163,
      "low": 1140,
      "volume": 114662
    },
    {
      "date": "2024-05-02",
      "price": 1090,
      "open": 1150,
      "high": 1151,
      "low": 1080,
      "volume": 310432
    },
    {
      "date": "2024-05-03",
      "price": 1098,
      "open": 1103,
      "high": 1127,
      "low": 1083,
      "volume": 74246
    },
    {
      "date": "2024-05-07",
      "price": 1097,
      "open": 1100,
      "high": 1100,
      "low": 1084,
      "volume": 68462
    },
    {
      "date": "2024-05-08",
      "price": 1102,
      "open": 1097,
      "high": 1106,
      "low": 1092,
      "volume": 33368
    },
    {
      "date": "2024-05-09",
      "price": 1107,
      "open": 1102,
      "high": 1128,
      "low": 1098,
      "volume": 60716
    },
    {
      "date": "2024-05-10",
      "price": 1100,
      "open": 1129,
      "high": 1129,
      "low": 1060,
      "volume": 121168
    },
    {
      "date": "2024-05-13",
      "price": 1079,
      "open": 1100,
      "high": 1100,
      "low": 1063,
      "volume": 80638
    },
    {
      "date": "2024-05-14",
      "price": 1085,
      "open": 1079,
      "high": 1098,
      "low": 1075,
      "volume": 54534
    },
    {
      "date": "2024-05-16",
      "price": 1104,
      "open": 1086,
      "high": 1132,
      "low": 1086,
      "volume": 42455
    },
    {
      "date": "2024-05-17",
      "price": 1069,
      "open": 1105,
      "high": 1139,
      "low": 1050,
      "volume": 122118
    },
    {
      "date": "2024-05-20",
      "price": 1067,
      "open": 1069,
      "high": 1070,
      "low": 1041,
      "volume": 52038
    },
    {
      "date": "2024-05-21",
      "price": 1067,
      "open": 1049,
      "high": 1067,
      "low": 1045,
      "volume": 102463
    },
    {
      "date": "2024-05-22",
      "price": 1061,
      "open": 1068,
      "high": 1068,
      "low": 1043,
      "volume": 142255
    },
    {
      "date": "2024-05-23",
      "price": 1044,
      "open": 1051,
      "high": 1060,
      "low": 1034,
      "volume": 79003
    },
    {
      "date": "2024-05-24",
      "price": 1067,
      "open": 1044,
      "high": 1067,
      "low": 1035,
      "volume": 20288
    },
    {
      "date": "2024-05-27",
      "price": 1070,
      "open": 1067,
      "high": 1078,
      "low": 1030,
      "volume": 100999
    },
    {
      "date": "2024-05-28",
      "price": 1055,
      "open": 1048,
      "high": 1072,
      "low": 1045,
      "volume": 36175
    },
    {
      "date": "2024-05-29",
      "price": 1050,
      "open": 1043,
      "high": 1057,
      "low": 1028,
      "volume": 75695
    },
    {
      "date": "2024-05-30",
      "price": 1044,
      "open": 1041,
      "high": 1060,
      "low": 1027,
      "volume": 36264
    },
    {
      "date": "2024-05-31",
      "price": 1024,
      "open": 1030,
      "high": 1035,
      "low": 1015,
      "volume": 44821
    },
    {
      "date": "2024-06-03",
      "price": 1012,
      "open": 1010,
      "high": 1024,
      "low": 1009,
      "volume": 86796
    },
    {
      "date": "2024-06-04",
      "price": 1015,
      "open": 1012,
      "high": 1032,
      "low": 1005,
      "volume": 30380
    },
    {
      "date": "2024-06-05",
      "price": 1013,
      "open": 1037,
      "high": 1037,
      "low": 1000,
      "volume": 124040
    },
    {
      "date": "2024-06-07",
      "price": 1012,
      "open": 1001,
      "high": 1013,
      "low": 1000,
      "volume": 37624
    },
    {
      "date": "2024-06-10",
      "price": 1000,
      "open": 1038,
      "high": 1038,
      "low": 975,
      "volume": 47499
    },
    {
      "date": "2024-06-11",
      "price": 1013,
      "open": 1001,
      "high": 1014,
      "low": 1001,
      "volume": 42101
    },
    {
      "date": "2024-06-12",
      "price": 1009,
      "open": 1013,
      "high": 1013,
      "low": 1006,
      "volume": 13885
    },
    {
      "date": "2024-06-13",
      "price": 1007,
      "open": 1003,
      "high": 1018,
      "low": 1002,
      "volume": 39560
    },
    {
      "date": "2024-06-14",
      "price": 993,
      "open": 1006,
      "high": 1006,
      "low": 992,
      "volume": 96568
    },
    {
      "date": "2024-06-17",
      "price": 969,
      "open": 993,
      "high": 993,
      "low": 947,
      "volume": 168746
    },
    {
      "date": "2024-06-18",
      "price": 923,
      "open": 969,
      "high": 969,
      "low": 873,
      "volume": 332286
    },
    {
      "date": "2024-06-19",
      "price": 917,
      "open": 924,
      "high": 928,
      "low": 903,
      "volume": 38361
    },
    {
      "date": "2024-06-20",
      "price": 904,
      "open": 927,
      "high": 928,
      "low": 904,
      "volume": 52959
    },
    {
      "date": "2024-06-21",
      "price": 901,
      "open": 925,
      "high": 928,
      "low": 877,
      "volume": 50840
    },
    {
      "date": "2024-06-24",
      "price": 890,
      "open": 901,
      "high": 916,
      "low": 862,
      "volume": 109150
    },
    {
      "date": "2024-06-25",
      "price": 923,
      "open": 900,
      "high": 978,
      "low": 880,
      "volume": 118796
    },
    {
      "date": "2024-06-26",
      "price": 949,
      "open": 924,
      "high": 960,
      "low": 916,
      "volume": 99171
    },
    {
      "date": "2024-06-27",
      "price": 886,
      "open": 949,
      "high": 949,
      "low": 880,
      "volume": 157539
    },
    {
      "date": "2024-06-28",
      "price": 876,
      "open": 886,
      "high": 898,
      "low": 864,
      "volume": 99400
    },
    {
      "date": "2024-07-01",
      "price": 840,
      "open": 876,
      "high": 900,
      "low": 840,
      "volume": 82653
    },
    {
      "date": "2024-07-02",
      "price": 839,
      "open": 840,
      "high": 851,
      "low": 827,
      "volume": 66640
    },
    {
      "date": "2024-07-03",
      "price": 888,
      "open": 839,
      "high": 897,
      "low": 803,
      "volume": 347637
    },
    {
      "date": "2024-07-04",
      "price": 829,
      "open": 888,
      "high": 895,
      "low": 818,
      "volume": 356684
    },
    {
      "date": "2024-07-05",
      "price": 831,
      "open": 831,
      "high": 870,
      "low": 823,
      "volume": 152660
    },
    {
      "date": "2024-07-08",
      "price": 841,
      "open": 831,
      "high": 849,
      "low": 826,
      "volume": 70386
    },
    {
      "date": "2024-07-09",
      "price": 867,
      "open": 849,
      "high": 867,
      "low": 835,
      "volume": 23380
    },
    {
      "date": "2024-07-10",
      "price": 865,
      "open": 868,
      "high": 874,
      "low": 852,
      "volume": 34013
    },
    {
      "date": "2024-07-11",
      "price": 840,
      "open": 865,
      "high": 866,
      "low": 835,
      "volume": 34854
    },
    {
      "date": "2024-07-12",
      "price": 841,
      "open": 849,
      "high": 867,
      "low": 820,
      "volume": 36030
    },
    {
      "date": "2024-07-15",
      "price": 842,
      "open": 841,
      "high": 855,
      "low": 829,
      "volume": 13715
    },
    {
      "date": "2024-07-16",
      "price": 845,
      "open": 856,
      "high": 856,
      "low": 832,
      "volume": 32922
    },
    {
      "date": "2024-07-17",
      "price": 861,
      "open": 845,
      "high": 865,
      "low": 840,
      "volume": 48519
    },
    {
      "date": "2024-07-18",
      "price": 845,
      "open": 861,
      "high": 861,
      "low": 840,
      "volume": 29196
    },
    {
      "date": "2024-07-19",
      "price": 845,
      "open": 836,
      "high": 860,
      "low": 836,
      "volume": 16921
    },
    {
      "date": "2024-07-22",
      "price": 770,
      "open": 845,
      "high": 845,
      "low": 765,
      "volume": 97340
    },
    {
      "date": "2024-07-23",
      "price": 788,
      "open": 772,
      "high": 789,
      "low": 772,
      "volume": 55556
    },
    {
      "date": "2024-07-24",
      "price": 778,
      "open": 788,
      "high": 788,
      "low": 762,
      "volume": 53138
    },
    {
      "date": "2024-07-25",
      "price": 757,
      "open": 778,
      "high": 778,
      "low": 736,
      "volume": 56638
    },
    {
      "date": "2024-07-26",
      "price": 745,
      "open": 757,
      "high": 757,
      "low": 739,
      "volume": 59898
    },
    {
      "date": "2024-07-29",
      "price": 749,
      "open": 745,
      "high": 774,
      "low": 742,
      "volume": 35197
    },
    {
      "date": "2024-07-30",
      "price": 730,
      "open": 749,
      "high": 749,
      "low": 730,
      "volume": 22371
    },
    {
      "date": "2024-07-31",
      "price": 735,
      "open": 732,
      "high": 757,
      "low": 730,
      "volume": 48524
    },
    {
      "date": "2024-08-01",
      "price": 753,
      "open": 735,
      "high": 789,
      "low": 735,
      "volume": 40596
    },
    {
      "date": "2024-08-02",
      "price": 739,
      "open": 753,
      "high": 753,
      "low": 730,
      "volume": 44891
    },
    {
      "date": "2024-08-05",
      "price": 728,
      "open": 739,
      "high": 739,
      "low": 688,
      "volume": 93713
    },
    {
      "date": "2024-08-06",
      "price": 723,
      "open": 728,
      "high": 728,
      "low": 700,
      "volume": 29159
    },
    {
      "date": "2024-08-07",
      "price": 703,
      "open": 715,
      "high": 723,
      "low": 697,
      "volume": 56570
    },
    {
      "date": "2024-08-08",
      "price": 655,
      "open": 695,
      "high": 704,
      "low": 652,
      "volume": 46043
    },
    {
      "date": "2024-08-09",
      "price": 691,
      "open": 655,
      "high": 697,
      "low": 655,
      "volume": 44280
    },
    {
      "date": "2024-08-12",
      "price": 727,
      "open": 691,
      "high": 730,
      "low": 691,
      "volume": 24689
    },
    {
      "date": "2024-08-13",
      "price": 715,
      "open": 727,
      "high": 736,
      "low": 710,
      "volume": 15948
    },
    {
      "date": "2024-08-14",
      "price": 735,
      "open": 715,
      "high": 735,
      "low": 715,
      "volume": 24411
    },
    {
      "date": "2024-08-16",
      "price": 733,
      "open": 735,
      "high": 746,
      "low": 730,
      "volume": 22443
    },
    {
      "date": "2024-08-19",
      "price": 743,
      "open": 734,
      "high": 750,
      "low": 733,
      "volume": 16529
    },
    {
      "date": "2024-08-20",
      "price": 760,
      "open": 742,
      "high": 770,
      "low": 734,
      "volume": 21349
    },
    {
      "date": "2024-08-21",
      "price": 776,
      "open": 752,
      "high": 779,
      "low": 746,
      "volume": 31572
    },
    {
      "date": "2024-08-22",
      "price": 760,
      "open": 776,
      "high": 776,
      "low": 760,
      "volume": 12982
    },
    {
      "date": "2024-08-23",
      "price": 783,
      "open": 759,
      "high": 799,
      "low": 754,
      "volume": 13097
    },
    {
      "date": "2024-08-26",
      "price": 720,
      "open": 779,
      "high": 784,
      "low": 720,
      "volume": 56654
    },
    {
      "date": "2024-08-27",
      "price": 724,
      "open": 720,
      "high": 745,
      "low": 719,
      "volume": 29391
    },
    {
      "date": "2024-08-28",
      "price": 741,
      "open": 724,
      "high": 749,
      "low": 724,
      "volume": 11286
    },
    {
      "date": "2024-08-29",
      "price": 744,
      "open": 741,
      "high": 767,
      "low": 729,
      "volume": 44393
    },
    {
      "date": "2024-08-30",
      "price": 735,
      "open": 744,
      "high": 762,
      "low": 735,
      "volume": 51875
    },
    {
      "date": "2024-09-02",
      "price": 736,
      "open": 735,
      "high": 762,
      "low": 731,
      "volume": 18250
    },
    {
      "date": "2024-09-03",
      "price": 800,
      "open": 736,
      "high": 956,
      "low": 736,
      "volume": 7283535
    },
    {
      "date": "2024-09-04",
      "price": 692,
      "open": 741,
      "high": 764,
      "low": 680,
      "volume": 609440
    },
    {
      "date": "2024-09-05",
      "price": 711,
      "open": 693,
      "high": 728,
      "low": 685,
      "volume": 198012
    },
    {
      "date": "2024-09-06",
      "price": 684,
      "open": 727,
      "high": 727,
      "low": 679,
      "volume": 128660
    },
    {
      "date": "2024-09-09",
      "price": 689,
      "open": 684,
      "high": 691,
      "low": 669,
      "volume": 97246
    },
    {
      "date": "2024-09-10",
      "price": 686,
      "open": 689,
      "high": 709,
      "low": 683,
      "volume": 92510
    },
    {
      "date": "2024-09-11",
      "price": 671,
      "open": 679,
      "high": 686,
      "low": 661,
      "volume": 60062
    },
    {
      "date": "2024-09-12",
      "price": 681,
      "open": 672,
      "high": 689,
      "low": 672,
      "volume": 75091
    },
    {
      "date": "2024-09-13",
      "price": 683,
      "open": 682,
      "high": 699,
      "low": 682,
      "volume": 62413
    },
    {
      "date": "2024-09-19",
      "price": 700,
      "open": 684,
      "high": 700,
      "low": 684,
      "volume": 37238
    },
    {
      "date": "2024-09-20",
      "price": 698,
      "open": 700,
      "high": 700,
      "low": 693,
      "volume": 45752
    },
    {
      "date": "2024-09-23",
      "price": 699,
      "open": 697,
      "high": 709,
      "low": 693,
      "volume": 57408
    },
    {
      "date": "2024-09-24",
      "price": 704,
      "open": 692,
      "high": 704,
      "low": 684,
      "volume": 27577
    },
    {
      "date": "2024-09-25",
      "price": 705,
      "open": 698,
      "high": 716,
      "low": 690,
      "volume": 51081
    },
    {
      "date": "2024-09-26",
      "price": 733,
      "open": 698,
      "high": 740,
      "low": 690,
      "volume": 97938
    },
    {
      "date": "2024-09-27",
      "price": 702,
      "open": 725,
      "high": 743,
      "low": 699,
      "volume": 100736
    },
    {
      "date": "2024-09-30",
      "price": 728,
      "open": 730,
      "high": 730,
      "low": 700,
      "volume": 19664
    },
    {
      "date": "2024-10-02",
      "price": 724,
      "open": 728,
      "high": 728,
      "low": 710,
      "volume": 23508
    },
    {
      "date": "2024-10-04",
      "price": 717,
      "open": 720,
      "high": 724,
      "low": 715,
      "volume": 21429
    },
    {
      "date": "2024-10-07",
      "price": 728,
      "open": 710,
      "high": 739,
      "low": 710,
      "volume": 22759
    },
    {
      "date": "2024-10-08",
      "price": 709,
      "open": 719,
      "high": 730,
      "low": 709,
      "volume": 48791
    },
    {
      "date": "2024-10-10",
      "price": 715,
      "open": 710,
      "high": 733,
      "low": 710,
      "volume": 33829
    },
    {
      "date": "2024-10-11",
      "price": 717,
      "open": 720,
      "high": 730,
      "low": 712,
      "volume": 19691
    },
    {
      "date": "2024-10-14",
      "price": 715,
      "open": 712,
      "high": 732,
      "low": 706,
      "volume": 70890
    },
    {
      "date": "2024-10-15",
      "price": 715,
      "open": 715,
      "high": 739,
      "low": 715,
      "volume": 46800
    },
    {
      "date": "2024-10-16",
      "price": 712,
      "open": 729,
      "high": 729,
      "low": 712,
      "volume": 50596
    },
    {
      "date": "2024-10-17",
      "price": 723,
      "open": 712,
      "high": 729,
      "low": 712,
      "volume": 33773
    },
    {
      "date": "2024-10-18",
      "price": 719,
      "open": 740,
      "high": 748,
      "low": 719,
      "volume": 29760
    },
    {
      "date": "2024-10-21",
      "price": 740,
      "open": 715,
      "high": 744,
      "low": 714,
      "volume": 43817
    },
    {
      "date": "2024-10-22",
      "price": 735,
      "open": 740,
      "high": 754,
      "low": 734,
      "volume": 60781
    },
    {
      "date": "2024-10-23",
      "price": 743,
      "open": 750,
      "high": 752,
      "low": 730,
      "volume": 18312
    },
    {
      "date": "2024-10-24",
      "price": 710,
      "open": 743,
      "high": 743,
      "low": 710,
      "volume": 20202
    },
    {
      "date": "2024-10-25",
      "price": 692,
      "open": 710,
      "high": 745,
      "low": 692,
      "volume": 45942
    },
    {
      "date": "2024-10-28",
      "price": 680,
      "open": 692,
      "high": 732,
      "low": 670,
      "volume": 92781
    },
    {
      "date": "2024-10-29",
      "price": 671,
      "open": 680,
      "high": 701,
      "low": 670,
      "volume": 53198
    },
    {
      "date": "2024-10-30",
      "price": 681,
      "open": 695,
      "high": 727,
      "low": 678,
      "volume": 20315
    },
    {
      "date": "2024-10-31",
      "price": 693,
      "open": 682,
      "high": 703,
      "low": 682,
      "volume": 24605
    },
    {
      "date": "2024-11-01",
      "price": 699,
      "open": 717,
      "high": 824,
      "low": 693,
      "volume": 887457
    },
    {
      "date": "2024-11-04",
      "price": 730,
      "open": 699,
      "high": 750,
      "low": 682,
      "volume": 102051
    },
    {
      "date": "2024-11-05",
      "price": 800,
      "open": 766,
      "high": 810,
      "low": 728,
      "volume": 250052
    },
    {
      "date": "2024-11-06",
      "price": 822,
      "open": 799,
      "high": 840,
      "low": 785,
      "volume": 203674
    },
    {
      "date": "2024-11-07",
      "price": 815,
      "open": 822,
      "high": 835,
      "low": 804,
      "volume": 60055
    },
    {
      "date": "2024-11-08",
      "price": 792,
      "open": 815,
      "high": 832,
      "low": 780,
      "volume": 50798
    },
    {
      "date": "2024-11-11",
      "price": 746,
      "open": 792,
      "high": 792,
      "low": 713,
      "volume": 102708
    },
    {
      "date": "2024-11-12",
      "price": 710,
      "open": 736,
      "high": 749,
      "low": 707,
      "volume": 54302
    },
    {
      "date": "2024-11-13",
      "price": 713,
      "open": 701,
      "high": 717,
      "low": 679,
      "volume": 51788
    },
    {
      "date": "2024-11-14",
      "price": 649,
      "open": 703,
      "high": 706,
      "low": 645,
      "volume": 185416
    },
    {
      "date": "2024-11-15",
      "price": 648,
      "open": 642,
      "high": 656,
      "low": 642,
      "volume": 69729
    },
    {
      "date": "2024-11-18",
      "price": 625,
      "open": 648,
      "high": 648,
      "low": 610,
      "volume": 59211
    },
    {
      "date": "2024-11-19",
      "price": 605,
      "open": 625,
      "high": 652,
      "low": 563,
      "volume": 206749
    },
    {
      "date": "2024-11-20",
      "price": 603,
      "open": 598,
      "high": 649,
      "low": 598,
      "volume": 75689
    },
    {
      "date": "2024-11-21",
      "price": 662,
      "open": 601,
      "high": 718,
      "low": 600,
      "volume": 311590
    },
    {
      "date": "2024-11-22",
      "price": 682,
      "open": 646,
      "high": 694,
      "low": 646,
      "volume": 51412
    },
    {
      "date": "2024-11-25",
      "price": 674,
      "open": 675,
      "high": 700,
      "low": 663,
      "volume": 31357
    },
    {
      "date": "2024-11-26",
      "price": 690,
      "open": 674,
      "high": 691,
      "low": 674,
      "volume": 29434
    },
    {
      "date": "2024-11-27",
      "price": 713,
      "open": 696,
      "high": 739,
      "low": 684,
      "volume": 74596
    },
    {
      "date": "2024-11-28",
      "price": 675,
      "open": 717,
      "high": 740,
      "low": 675,
      "volume": 50136
    },
    {
      "date": "2024-11-29",
      "price": 680,
      "open": 696,
      "high": 709,
      "low": 675,
      "volume": 31245
    },
    {
      "date": "2024-12-02",
      "price": 689,
      "open": 680,
      "high": 707,
      "low": 674,
      "volume": 38100
    },
    {
      "date": "2024-12-03",
      "price": 658,
      "open": 689,
      "high": 689,
      "low": 639,
      "volume": 41505
    },
    {
      "date": "2024-12-04",
      "price": 656,
      "open": 655,
      "high": 689,
      "low": 653,
      "volume": 30054
    },
    {
      "date": "2024-12-05",
      "price": 641,
      "open": 656,
      "high": 689,
      "low": 641,
      "volume": 15260
    },
    {
      "date": "2024-12-06",
      "price": 619,
      "open": 677,
      "high": 677,
      "low": 619,
      "volume": 32135
    },
    {
      "date": "2024-12-09",
      "price": 591,
      "open": 618,
      "high": 618,
      "low": 586,
      "volume": 25154
    },
    {
      "date": "2024-12-10",
      "price": 616,
      "open": 601,
      "high": 630,
      "low": 595,
      "volume": 16078
    },
    {
      "date": "2024-12-11",
      "price": 657,
      "open": 616,
      "high": 661,
      "low": 616,
      "volume": 25682
    },
    {
      "date": "2024-12-12",
      "price": 660,
      "open": 660,
      "high": 673,
      "low": 648,
      "volume": 10085
    },
    {
      "date": "2024-12-13",
      "price": 650,
      "open": 640,
      "high": 675,
      "low": 640,
      "volume": 31120
    },
    {
      "date": "2024-12-16",
      "price": 642,
      "open": 643,
      "high": 652,
      "low": 635,
      "volume": 23059
    },
    {
      "date": "2024-12-17",
      "price": 646,
      "open": 630,
      "high": 672,
      "low": 628,
      "volume": 30398
    },
    {
      "date": "2024-12-18",
      "price": 639,
      "open": 642,
      "high": 672,
      "low": 630,
      "volume": 16151
    },
    {
      "date": "2024-12-19",
      "price": 638,
      "open": 639,
      "high": 648,
      "low": 631,
      "volume": 16388
    },
    {
      "date": "2024-12-20",
      "price": 632,
      "open": 660,
      "high": 660,
      "low": 629,
      "volume": 10989
    },
    {
      "date": "2024-12-23",
      "price": 622,
      "open": 632,
      "high": 634,
      "low": 620,
      "volume": 18432
    },
    {
      "date": "2024-12-24",
      "price": 598,
      "open": 620,
      "high": 650,
      "low": 598,
      "volume": 24269
    },
    {
      "date": "2024-12-26",
      "price": 569,
      "open": 608,
      "high": 620,
      "low": 569,
      "volume": 54636
    },
    {
      "date": "2024-12-27",
      "price": 570,
      "open": 569,
      "high": 709,
      "low": 560,
      "volume": 500279
    },
    {
      "date": "2024-12-30",
      "price": 580,
      "open": 571,
      "high": 626,
      "low": 571,
      "volume": 50662
    },
    {
      "date": "2025-01-02",
      "price": 588,
      "open": 584,
      "high": 601,
      "low": 577,
      "volume": 40232
    },
    {
      "date": "2025-01-03",
      "price": 593,
      "open": 590,
      "high": 599,
      "low": 583,
      "volume": 30006
    },
    {
      "date": "2025-01-06",
      "price": 595,
      "open": 599,
      "high": 599,
      "low": 575,
      "volume": 102791
    },
    {
      "date": "2025-01-07",
      "price": 607,
      "open": 587,
      "high": 608,
      "low": 587,
      "volume": 23814
    },
    {
      "date": "2025-01-08",
      "price": 613,
      "open": 608,
      "high": 632,
      "low": 605,
      "volume": 44809
    },
    {
      "date": "2025-01-09",
      "price": 613,
      "open": 613,
      "high": 619,
      "low": 605,
      "volume": 5798
    },
    {
      "date": "2025-01-10",
      "price": 598,
      "open": 613,
      "high": 613,
      "low": 595,
      "volume": 33717
    },
    {
      "date": "2025-01-13",
      "price": 569,
      "open": 600,
      "high": 600,
      "low": 565,
      "volume": 106906
    },
    {
      "date": "2025-01-14",
      "price": 583,
      "open": 575,
      "high": 620,
      "low": 575,
      "volume": 86535
    },
    {
      "date": "2025-01-15",
      "price": 581,
      "open": 616,
      "high": 616,
      "low": 579,
      "volume": 51849
    },
    {
      "date": "2025-01-16",
      "price": 597,
      "open": 581,
      "high": 614,
      "low": 581,
      "volume": 24142
    },
    {
      "date": "2025-01-17",
      "price": 584,
      "open": 597,
      "high": 600,
      "low": 583,
      "volume": 38439
    },
    {
      "date": "2025-01-20",
      "price": 562,
      "open": 585,
      "high": 600,
      "low": 554,
      "volume": 95150
    },
    {
      "date": "2025-01-21",
      "price": 560,
      "open": 588,
      "high": 588,
      "low": 552,
      "volume": 66429
    },
    {
      "date": "2025-01-22",
      "price": 544,
      "open": 560,
      "high": 563,
      "low": 540,
      "volume": 93287
    },
    {
      "date": "2025-01-23",
      "price": 560,
      "open": 544,
      "high": 707,
      "low": 544,
      "volume": 3329085
    },
    {
      "date": "2025-01-24",
      "price": 560,
      "open": 562,
      "high": 660,
      "low": 556,
      "volume": 941424
    },
    {
      "date": "2025-01-31",
      "price": 546,
      "open": 560,
      "high": 584,
      "low": 541,
      "volume": 168451
    },
    {
      "date": "2025-02-03",
      "price": 521,
      "open": 546,
      "high": 559,
      "low": 502,
      "volume": 94931
    },
    {
      "date": "2025-02-04",
      "price": 523,
      "open": 516,
      "high": 554,
      "low": 511,
      "volume": 52009
    },
    {
      "date": "2025-02-05",
      "price": 530,
      "open": 554,
      "high": 554,
      "low": 516,
      "volume": 58137
    },
    {
      "date": "2025-02-06",
      "price": 525,
      "open": 552,
      "high": 552,
      "low": 520,
      "volume": 39894
    },
    {
      "date": "2025-02-07",
      "price": 528,
      "open": 525,
      "high": 548,
      "low": 525,
      "volume": 21351
    },
    {
      "date": "2025-02-10",
      "price": 517,
      "open": 524,
      "high": 547,
      "low": 505,
      "volume": 51633
    },
    {
      "date": "2025-02-11",
      "price": 517,
      "open": 517,
      "high": 538,
      "low": 510,
      "volume": 71747
    },
    {
      "date": "2025-02-12",
      "price": 516,
      "open": 515,
      "high": 523,
      "low": 512,
      "volume": 15012
    },
    {
      "date": "2025-02-13",
      "price": 507,
      "open": 510,
      "high": 518,
      "low": 505,
      "volume": 49953
    },
    {
      "date": "2025-02-14",
      "price": 506,
      "open": 515,
      "high": 523,
      "low": 501,
      "volume": 65894
    },
    {
      "date": "2025-02-17",
      "price": 512,
      "open": 506,
      "high": 525,
      "low": 503,
      "volume": 23030
    },
    {
      "date": "2025-02-18",
      "price": 518,
      "open": 512,
      "high": 519,
      "low": 510,
      "volume": 33400
    },
    {
      "date": "2025-02-19",
      "price": 519,
      "open": 514,
      "high": 524,
      "low": 510,
      "volume": 34538
    },
    {
      "date": "2025-02-20",
      "price": 517,
      "open": 519,
      "high": 525,
      "low": 513,
      "volume": 42305
    },
    {
      "date": "2025-02-21",
      "price": 517,
      "open": 548,
      "high": 548,
      "low": 513,
      "volume": 28196
    },
    {
      "date": "2025-02-24",
      "price": 516,
      "open": 517,
      "high": 527,
      "low": 508,
      "volume": 37303
    },
    {
      "date": "2025-02-25",
      "price": 513,
      "open": 526,
      "high": 526,
      "low": 513,
      "volume": 18825
    },
    {
      "date": "2025-02-26",
      "price": 516,
      "open": 509,
      "high": 523,
      "low": 509,
      "volume": 22475
    },
    {
      "date": "2025-02-27",
      "price": 510,
      "open": 516,
      "high": 522,
      "low": 508,
      "volume": 30103
    },
    {
      "date": "2025-02-28",
      "price": 504,
      "open": 510,
      "high": 517,
      "low": 501,
      "volume": 31433
    },
    {
      "date": "2025-03-04",
      "price": 495,
      "open": 504,
      "high": 514,
      "low": 494,
      "volume": 31843
    },
    {
      "date": "2025-03-05",
      "price": 496,
      "open": 519,
      "high": 520,
      "low": 495,
      "volume": 48340
    },
    {
      "date": "2025-03-06",
      "price": 496,
      "open": 518,
      "high": 518,
      "low": 496,
      "volume": 27906
    },
    {
      "date": "2025-03-07",
      "price": 497,
      "open": 498,
      "high": 499,
      "low": 491,
      "volume": 29718
    },
    {
      "date": "2025-03-10",
      "price": 501,
      "open": 497,
      "high": 507,
      "low": 497,
      "volume": 35159
    },
    {
      "date": "2025-03-11",
      "price": 495,
      "open": 502,
      "high": 502,
      "low": 495,
      "volume": 27767
    },
    {
      "date": "2025-03-12",
      "price": 495,
      "open": 495,
      "high": 498,
      "low": 492,
      "volume": 10503
    },
    {
      "date": "2025-03-13",
      "price": 492,
      "open": 502,
      "high": 502,
      "low": 490,
      "volume": 15409
    },
    {
      "date": "2025-03-14",
      "price": 495,
      "open": 492,
      "high": 500,
      "low": 491,
      "volume": 11932
    },
    {
      "date": "2025-03-17",
      "price": 490,
      "open": 500,
      "high": 500,
      "low": 490,
      "volume": 27305
    },
    {
      "date": "2025-03-18",
      "price": 480,
      "open": 484,
      "high": 495,
      "low": 479,
      "volume": 82308
    },
    {
      "date": "2025-03-19",
      "price": 484,
      "open": 480,
      "high": 488,
      "low": 476,
      "volume": 68957
    },
    {
      "date": "2025-03-20",
      "price": 485,
      "open": 486,
      "high": 494,
      "low": 485,
      "volume": 44028
    },
    {
      "date": "2025-03-21",
      "price": 480,
      "open": 485,
      "high": 491,
      "low": 480,
      "volume": 36568
    },
    {
      "date": "2025-03-24",
      "price": 481,
      "open": 482,
      "high": 500,
      "low": 480,
      "volume": 36266
    },
    {
      "date": "2025-03-25",
      "price": 487,
      "open": 482,
      "high": 490,
      "low": 481,
      "volume": 21010
    },
    {
      "date": "2025-03-26",
      "price": 487,
      "open": 491,
      "high": 492,
      "low": 487,
      "volume": 44613
    },
    {
      "date": "2025-03-27",
      "price": 491,
      "open": 492,
      "high": 492,
      "low": 487,
      "volume": 37153
    },
    {
      "date": "2025-03-28",
      "price": 475,
      "open": 492,
      "high": 492,
      "low": 470,
      "volume": 39890
    },
    {
      "date": "2025-03-31",
      "price": 466,
      "open": 475,
      "high": 475,
      "low": 465,
      "volume": 34274
    },
    {
      "date": "2025-04-01",
      "price": 463,
      "open": 466,
      "high": 467,
      "low": 460,
      "volume": 65009
    },
    {
      "date": "2025-04-02",
      "price": 475,
      "open": 465,
      "high": 475,
      "low": 463,
      "volume": 59113
    },
    {
      "date": "2025-04-03",
      "price": 464,
      "open": 475,
      "high": 478,
      "low": 460,
      "volume": 57033
    },
    {
      "date": "2025-04-04",
      "price": 467,
      "open": 464,
      "high": 467,
      "low": 464,
      "volume": 25424
    },
    {
      "date": "2025-04-07",
      "price": 453,
      "open": 462,
      "high": 464,
      "low": 431,
      "volume": 40824
    },
    {
      "date": "2025-04-08",
      "price": 439,
      "open": 453,
      "high": 453,
      "low": 439,
      "volume": 36243
    },
    {
      "date": "2025-04-09",
      "price": 437,
      "open": 442,
      "high": 452,
      "low": 437,
      "volume": 22032
    },
    {
      "date": "2025-04-10",
      "price": 449,
      "open": 442,
      "high": 463,
      "low": 437,
      "volume": 30045
    },
    {
      "date": "2025-04-11",
      "price": 454,
      "open": 449,
      "high": 462,
      "low": 449,
      "volume": 13833
    },
    {
      "date": "2025-04-14",
      "price": 463,
      "open": 454,
      "high": 464,
      "low": 450,
      "volume": 18884
    },
    {
      "date": "2025-04-15",
      "price": 460,
      "open": 463,
      "high": 470,
      "low": 460,
      "volume": 14491
    },
    {
      "date": "2025-04-16",
      "price": 474,
      "open": 460,
      "high": 529,
      "low": 460,
      "volume": 714681
    },
    {
      "date": "2025-04-17",
      "price": 468,
      "open": 487,
      "high": 487,
      "low": 467,
      "volume": 116513
    },
    {
      "date": "2025-04-18",
      "price": 476,
      "open": 472,
      "high": 483,
      "low": 468,
      "volume": 82363
    },
    {
      "date": "2025-04-21",
      "price": 465,
      "open": 476,
      "high": 476,
      "low": 461,
      "volume": 37537
    },
    {
      "date": "2025-04-22",
      "price": 463,
      "open": 466,
      "high": 472,
      "low": 462,
      "volume": 26587
    },
    {
      "date": "2025-04-23",
      "price": 467,
      "open": 476,
      "high": 476,
      "low": 465,
      "volume": 17225
    },
    {
      "date": "2025-04-24",
      "price": 466,
      "open": 467,
      "high": 474,
      "low": 465,
      "volume": 17342
    },
    {
      "date": "2025-04-25",
      "price": 467,
      "open": 474,
      "high": 495,
      "low": 466,
      "volume": 152760
    },
    {
      "date": "2025-04-28",
      "price": 478,
      "open": 470,
      "high": 481,
      "low": 468,
      "volume": 41201
    },
    {
      "date": "2025-04-29",
      "price": 466,
      "open": 478,
      "high": 481,
      "low": 466,
      "volume": 51372
    },
    {
      "date": "2025-04-30",
      "price": 470,
      "open": 467,
      "high": 472,
      "low": 463,
      "volume": 51401
    }
  ]
}